{
	"info": {
		"_postman_id": "36cb6def-6e79-486b-9bcb-5bf4523ec5b2",
		"name": "sap-connector-octane-utility",
		"schema": "https://schema.getpostman.com/json/collection/v2.1.0/collection.json"
	},
	"item": [
		{
			"name": "requirements",
			"item": [
				{
					"name": "authenticate",
					"event": [
						{
							"listen": "test",
							"script": {
								"exec": [
									"pm.environment.set(\"lwsso_cookie_key\", postman.getResponseCookie(\"LWSSO_COOKIE_KEY\").value)",
									"pm.environment.set(\"octane_user\", postman.getResponseCookie(\"OCTANE_USER\").value)",
									"//console.log (pm.environment.get(\"lwsso_cookie_key\"))",
									"//console.log (pm.environment.get(\"octane_user\"))",
									""
								],
								"type": "text/javascript"
							}
						}
					],
					"protocolProfileBehavior": {
						"disableUrlEncoding": false
					},
					"request": {
						"method": "POST",
						"header": [
							{
								"key": "Content-Type",
								"value": "application/json"
							}
						],
						"body": {
							"mode": "raw",
							"raw": "{\n    \"client_id\": \"{{client-id}}\",\n    \"client_secret\": \"{{client-secret}}\"\n}"
						},
						"url": {
							"raw": "http://{{baseUrl}}:{{port}}/authentication/sign_in",
							"protocol": "http",
							"host": [
								"{{baseUrl}}"
							],
							"port": "{{port}}",
							"path": [
								"authentication",
								"sign_in"
							]
						}
					},
					"response": []
				},
				{
					"name": "sap-branch",
					"request": {
						"method": "POST",
						"header": [
							{
								"key": "Content-Type",
								"value": "application/json"
							},
							{
								"key": "LWSSO_COOKIE_KEY",
								"value": "{{lwsso_cookie_key}}"
							},
							{
								"key": "OCTANE_USER",
								"value": "{{octane_user}}"
							},
							{
								"key": "{{header-key}}",
								"value": "{{header-value}}"
							}
						],
						"body": {
							"mode": "raw",
							"raw": "{\n    \"data\": [\n        {\n            \"entity_type\": \"requirement_document\",\n            \"label\": \"SAP Branch\",\n            \"name\": \"sap_branch_udf\",\n            \"subtype\": \"field_metadata_string\"\n        }\n    ]\n}"
						},
						"url": {
							"raw": "http://{{baseUrl}}:{{port}}/api/shared_spaces/{{ssid}}/workspaces/{{wsid}}/metadata_fields",
							"protocol": "http",
							"host": [
								"{{baseUrl}}"
							],
							"port": "{{port}}",
							"path": [
								"api",
								"shared_spaces",
								"{{ssid}}",
								"workspaces",
								"{{wsid}}",
								"metadata_fields"
							]
						}
					},
					"response": []
				},
				{
					"name": "sap-change-at",
					"request": {
						"method": "POST",
						"header": [
							{
								"key": "Content-Type",
								"value": "application/json"
							},
							{
								"key": "LWSSO_COOKIE_KEY",
								"value": "{{lwsso_cookie_key}}"
							},
							{
								"key": "OCTANE_USER",
								"value": "{{octane_user}}"
							},
							{
								"key": "{{header-key}}",
								"value": "{{header-value}}"
							}
						],
						"body": {
							"mode": "raw",
							"raw": "{\n    \"data\": [\n        {\n            \"entity_type\": \"requirement_document\",\n            \"label\": \"SAP Change at\",\n            \"name\": \"sap_change_at_udf\",\n            \"subtype\": \"field_metadata_date_time\"\n        }\n    ]\n}"
						},
						"url": {
							"raw": "http://{{baseUrl}}:8085/api/shared_spaces/{{ssid}}/workspaces/{{wsid}}/metadata_fields",
							"protocol": "http",
							"host": [
								"{{baseUrl}}"
							],
							"port": "8085",
							"path": [
								"api",
								"shared_spaces",
								"{{ssid}}",
								"workspaces",
								"{{wsid}}",
								"metadata_fields"
							]
						}
					},
					"response": []
				},
				{
					"name": "sap-change-by",
					"request": {
						"method": "POST",
						"header": [
							{
								"key": "Content-Type",
								"value": "application/json"
							},
							{
								"key": "LWSSO_COOKIE_KEY",
								"value": "{{lwsso_cookie_key}}"
							},
							{
								"key": "OCTANE_USER",
								"value": "{{octane_user}}"
							},
							{
								"key": "{{header-key}}",
								"value": "{{header-value}}"
							}
						],
						"body": {
							"mode": "raw",
							"raw": "{\n    \"data\": [\n        {\n            \"entity_type\": \"requirement_document\",\n            \"label\": \"SAP Change by\",\n            \"name\": \"sap_changeby_udf\",\n            \"subtype\": \"field_metadata_string\"\n        }\n    ]\n}"
						},
						"url": {
							"raw": "http://{{baseUrl}}:8085/api/shared_spaces/{{ssid}}/workspaces/{{wsid}}/metadata_fields",
							"protocol": "http",
							"host": [
								"{{baseUrl}}"
							],
							"port": "8085",
							"path": [
								"api",
								"shared_spaces",
								"{{ssid}}",
								"workspaces",
								"{{wsid}}",
								"metadata_fields"
							]
						}
					},
					"response": []
				},
				{
					"name": "sap-generated-source",
					"request": {
						"method": "POST",
						"header": [
							{
								"key": "Content-Type",
								"value": "application/json"
							},
							{
								"key": "LWSSO_COOKIE_KEY",
								"value": "{{lwsso_cookie_key}}"
							},
							{
								"key": "OCTANE_USER",
								"value": "{{octane_user}}"
							},
							{
								"key": "{{header-key}}",
								"value": "{{header-value}}"
							}
						],
						"body": {
							"mode": "raw",
							"raw": "{\n    \"data\": [\n        {\n            \"entity_type\": \"requirement_document\",\n            \"label\": \"SAP Node ID\",\n            \"name\": \"sap_nodeid_udf\",\n            \"subtype\": \"field_metadata_string\"\n        }\n    ]\n}"
						},
						"url": {
							"raw": "http://{{baseUrl}}:8085/api/shared_spaces/{{ssid}}/workspaces/{{wsid}}/metadata_fields",
							"protocol": "http",
							"host": [
								"{{baseUrl}}"
							],
							"port": "8085",
							"path": [
								"api",
								"shared_spaces",
								"{{ssid}}",
								"workspaces",
								"{{wsid}}",
								"metadata_fields"
							]
						}
					},
					"response": []
				},
				{
					"name": "sap-nodeid",
					"request": {
						"method": "POST",
						"header": [
							{
								"key": "Content-Type",
								"value": "application/json"
							},
							{
								"key": "LWSSO_COOKIE_KEY",
								"value": "{{lwsso_cookie_key}}"
							},
							{
								"key": "OCTANE_USER",
								"value": "{{octane_user}}"
							},
							{
								"key": "{{header-key}}",
								"value": "{{header-value}}"
							}
						],
						"body": {
							"mode": "raw",
							"raw": "{\n    \"data\": [\n        {\n            \"entity_type\": \"requirement_document\",\n            \"label\": \"SAP Generated Source\",\n            \"name\": \"sap_generated_source_udf\",\n            \"subtype\": \"field_metadata_string\"\n        }\n    ]\n}"
						},
						"url": {
							"raw": "http://{{baseUrl}}:8085/api/shared_spaces/{{ssid}}/workspaces/{{wsid}}/metadata_fields",
							"protocol": "http",
							"host": [
								"{{baseUrl}}"
							],
							"port": "8085",
							"path": [
								"api",
								"shared_spaces",
								"{{ssid}}",
								"workspaces",
								"{{wsid}}",
								"metadata_fields"
							]
						}
					},
					"response": []
				},
				{
					"name": "sap-node-type",
					"request": {
						"method": "POST",
						"header": [
							{
								"key": "Content-Type",
								"value": "application/json"
							},
							{
								"key": "LWSSO_COOKIE_KEY",
								"value": "{{lwsso_cookie_key}}"
							},
							{
								"key": "OCTANE_USER",
								"value": "{{octane_user}}"
							},
							{
								"key": "{{header-key}}",
								"value": "{{header-value}}"
							}
						],
						"body": {
							"mode": "raw",
							"raw": "{\n    \"data\": [\n        {\n            \"entity_type\": \"requirement_document\",\n            \"label\": \"SAP Node Type\",\n            \"name\": \"sap_node_type_udf\",\n            \"subtype\": \"field_metadata_string\"\n        }\n    ]\n}"
						},
						"url": {
							"raw": "http://{{baseUrl}}:8085/api/shared_spaces/{{ssid}}/workspaces/{{wsid}}/metadata_fields",
							"protocol": "http",
							"host": [
								"{{baseUrl}}"
							],
							"port": "8085",
							"path": [
								"api",
								"shared_spaces",
								"{{ssid}}",
								"workspaces",
								"{{wsid}}",
								"metadata_fields"
							]
						}
					},
					"response": []
				},
				{
					"name": "sap-parent-id",
					"request": {
						"method": "POST",
						"header": [
							{
								"key": "Content-Type",
								"value": "application/json"
							},
							{
								"key": "LWSSO_COOKIE_KEY",
								"value": "{{lwsso_cookie_key}}"
							},
							{
								"key": "OCTANE_USER",
								"value": "{{octane_user}}"
							},
							{
								"key": "{{header-key}}",
								"value": "{{header-value}}"
							}
						],
						"body": {
							"mode": "raw",
							"raw": "{\n    \"data\": [\n        {\n            \"entity_type\": \"requirement_document\",\n            \"label\": \"SAP Parent ID\",\n            \"name\": \"sap_parentid_udf\",\n            \"subtype\": \"field_metadata_string\"\n        }\n    ]\n}"
						},
						"url": {
							"raw": "http://{{baseUrl}}:8085/api/shared_spaces/{{ssid}}/workspaces/{{wsid}}/metadata_fields",
							"protocol": "http",
							"host": [
								"{{baseUrl}}"
							],
							"port": "8085",
							"path": [
								"api",
								"shared_spaces",
								"{{ssid}}",
								"workspaces",
								"{{wsid}}",
								"metadata_fields"
							]
						}
					},
					"response": []
				},
				{
					"name": "sap-scope",
					"request": {
						"method": "POST",
						"header": [
							{
								"key": "Content-Type",
								"value": "application/json"
							},
							{
								"key": "LWSSO_COOKIE_KEY",
								"value": "{{lwsso_cookie_key}}"
							},
							{
								"key": "OCTANE_USER",
								"value": "{{octane_user}}"
							},
							{
								"key": "{{header-key}}",
								"value": "{{header-value}}"
							}
						],
						"body": {
							"mode": "raw",
							"raw": "{\n    \"data\": [\n        {\n            \"entity_type\": \"requirement_document\",\n            \"label\": \"SAP Scope\",\n            \"name\": \"sap_scope_udf\",\n            \"subtype\": \"field_metadata_string\"\n        }\n    ]\n}"
						},
						"url": {
							"raw": "http://{{baseUrl}}:8085/api/shared_spaces/{{ssid}}/workspaces/{{wsid}}/metadata_fields",
							"protocol": "http",
							"host": [
								"{{baseUrl}}"
							],
							"port": "8085",
							"path": [
								"api",
								"shared_spaces",
								"{{ssid}}",
								"workspaces",
								"{{wsid}}",
								"metadata_fields"
							]
						}
					},
					"response": []
				},
				{
					"name": "sap-solution",
					"request": {
						"method": "POST",
						"header": [
							{
								"key": "Content-Type",
								"value": "application/json"
							},
							{
								"key": "LWSSO_COOKIE_KEY",
								"value": "{{lwsso_cookie_key}}"
							},
							{
								"key": "OCTANE_USER",
								"value": "{{octane_user}}"
							},
							{
								"key": "{{header-key}}",
								"value": "{{header-value}}"
							}
						],
						"body": {
							"mode": "raw",
							"raw": "{\n    \"data\": [\n        {\n            \"entity_type\": \"requirement_document\",\n            \"label\": \"SAP Solution\",\n            \"name\": \"sap_solution_udf\",\n            \"subtype\": \"field_metadata_string\"\n        }\n    ]\n}"
						},
						"url": {
							"raw": "http://{{baseUrl}}:8085/api/shared_spaces/{{ssid}}/workspaces/{{wsid}}/metadata_fields",
							"protocol": "http",
							"host": [
								"{{baseUrl}}"
							],
							"port": "8085",
							"path": [
								"api",
								"shared_spaces",
								"{{ssid}}",
								"workspaces",
								"{{wsid}}",
								"metadata_fields"
							]
						}
					},
					"response": []
				},
				{
					"name": "sap-tcaseassign",
					"request": {
						"method": "POST",
						"header": [
							{
								"key": "Content-Type",
								"value": "application/json"
							},
							{
								"key": "LWSSO_COOKIE_KEY",
								"value": "{{lwsso_cookie_key}}"
							},
							{
								"key": "OCTANE_USER",
								"value": "{{octane_user}}"
							},
							{
								"key": "{{header-key}}",
								"value": "{{header-value}}"
							}
						],
						"body": {
							"mode": "raw",
							"raw": "{\n    \"data\": [\n        {\n            \"entity_type\": \"requirement_document\",\n            \"label\": \"SAP TestCase Assignment\",\n            \"name\": \"sap_tcaseassign_udf\",\n            \"subtype\": \"field_metadata_string\"\n        }\n    ]\n}"
						},
						"url": {
							"raw": "http://{{baseUrl}}:8085/api/shared_spaces/{{ssid}}/workspaces/{{wsid}}/metadata_fields",
							"protocol": "http",
							"host": [
								"{{baseUrl}}"
							],
							"port": "8085",
							"path": [
								"api",
								"shared_spaces",
								"{{ssid}}",
								"workspaces",
								"{{wsid}}",
								"metadata_fields"
							]
						}
					},
					"response": []
				},
				{
					"name": "sap-node-path",
					"request": {
						"method": "POST",
						"header": [
							{
								"key": "Content-Type",
								"value": "application/json"
							},
							{
								"key": "LWSSO_COOKIE_KEY",
								"value": "{{lwsso_cookie_key}}"
							},
							{
								"key": "OCTANE_USER",
								"value": "{{octane_user}}"
							},
							{
								"key": "{{header-key}}",
								"value": "{{header-value}}"
							}
						],
						"body": {
							"mode": "raw",
							"raw": "{\n    \"data\": [\n        {\n            \"entity_type\": \"requirement_document\",\n            \"label\": \"SAP Node Path\",\n            \"name\": \"sap_node_path_udf\",\n            \"subtype\": \"field_metadata_string\"\n        }\n    ]\n}"
						},
						"url": {
							"raw": "http://{{baseUrl}}:8085/api/shared_spaces/{{ssid}}/workspaces/{{wsid}}/metadata_fields",
							"protocol": "http",
							"host": [
								"{{baseUrl}}"
							],
							"port": "8085",
							"path": [
								"api",
								"shared_spaces",
								"{{ssid}}",
								"workspaces",
								"{{wsid}}",
								"metadata_fields"
							]
						}
					},
					"response": []
				},
				{
					"name": "sap-req-form",
					"event": [
						{
							"listen": "test",
							"script": {
								"exec": [
									"var jsData = JSON.parse(responseBody);\r",
									"\r",
									"var id = jsData.data[0].id;\r",
									"pm.environment.set(\"req-form-id\", id);"
								],
								"type": "text/javascript"
							}
						}
					],
					"request": {
						"method": "POST",
						"header": [
							{
								"key": "Content-Type",
								"value": "application/json"
							},
							{
								"key": "LWSSO_COOKIE_KEY",
								"value": "{{lwsso_cookie_key}}"
							},
							{
								"key": "OCTANE_USER",
								"value": "{{octane_user}}"
							},
							{
								"key": "{{header-key}}",
								"value": "{{header-value}}"
							}
						],
						"body": {
							"mode": "raw",
							"raw": "{\n    \"data\": [\n        {\n            \"name\": \"sap-connector-req-form\",\n            \"body\": {\n                \"layout\": {\n                    \"sections\": [\n                        {\n                            \"title\": \"SAP Connector\",\n                            \"fields\": [\n                                {\n                                    \"name\": \"sap_branch_udf\",\n                                    \"size\": \"large\"\n                                },\n                                {\n                                    \"name\": \"sap_change_at_udf\",\n                                    \"size\": \"medium\"\n                                },\n                                {\n                                    \"name\": \"sap_changeby_udf\",\n                                    \"size\": \"medium\"\n                                },\n                                {\n                                    \"name\": \"sap_generated_source_udf\",\n                                    \"size\": \"medium\"\n                                },\n                                {\n                                    \"name\": \"sap_nodeid_udf\",\n                                    \"size\": \"medium\"\n                                },\n                                {\n                                    \"name\": \"sap_node_path_udf\",\n                                    \"size\": \"medium\"\n                                },\n                                {\n                                    \"name\": \"sap_node_type_udf\",\n                                    \"size\": \"medium\"\n                                },\n                                {\n                                    \"name\": \"sap_parentid_udf\",\n                                    \"size\": \"medium\"\n                                },\n                                {\n                                    \"name\": \"sappath_udf\",\n                                    \"size\": \"medium\"\n                                },\n                                {\n                                    \"name\": \"sap_scope_udf\",\n                                    \"size\": \"large\"\n                                },\n                                {\n                                    \"name\": \"sap_solution_udf\",\n                                    \"size\": \"medium\"\n                                },\n                                {\n                                    \"name\": \"sap_tcaseassign_udf\",\n                                    \"size\": \"medium\"\n                                }\n                            ]\n                        },\n                        {\n                            \"title\": \"General\",\n                            \"fields\": [\n                                {\n                                    \"name\": \"description\",\n                                    \"size\": \"large\"\n                                }\n                            ]\n                        }\n                    ]\n                }\n            },\n            \"is_default\": 0,\n            \"entity_type\": \"requirement\",\n            \"entity_subtype\": \"requirement_document\"\n        }\n    ]\n}"
						},
						"url": {
							"raw": "http://{{baseUrl}}:8085/api/shared_spaces/{{ssid}}/workspaces/{{wsid}}/form_layouts",
							"protocol": "http",
							"host": [
								"{{baseUrl}}"
							],
							"port": "8085",
							"path": [
								"api",
								"shared_spaces",
								"{{ssid}}",
								"workspaces",
								"{{wsid}}",
								"form_layouts"
							]
						}
					},
					"response": []
				},
				{
					"name": "sap-req-form-make-default",
					"event": [
						{
							"listen": "test",
							"script": {
								"exec": [
									""
								],
								"type": "text/javascript"
							}
						}
					],
					"request": {
						"method": "PUT",
						"header": [
							{
								"key": "Content-Type",
								"value": "application/json"
							},
							{
								"key": "LWSSO_COOKIE_KEY",
								"value": "{{lwsso_cookie_key}}"
							},
							{
								"key": "OCTANE_USER",
								"value": "{{octane_user}}"
							},
							{
								"key": "{{header-key}}",
								"value": "{{header-value}}"
							}
						],
						"body": {
							"mode": "raw",
							"raw": "{\n    \"data\": [\n        {\n            \"is_default\": 1,\n            \"id\": \"{{req-form-id}}\"\n        },\n        {\n            \"is_default\": 3,\n            \"id\": \"{{req-form-id}}\"\n        }\n    ]\n}"
						},
						"url": {
							"raw": "http://{{baseUrl}}:8085/api/shared_spaces/{{ssid}}/workspaces/{{wsid}}/form_layouts/",
							"protocol": "http",
							"host": [
								"{{baseUrl}}"
							],
							"port": "8085",
							"path": [
								"api",
								"shared_spaces",
								"{{ssid}}",
								"workspaces",
								"{{wsid}}",
								"form_layouts",
								""
							]
						}
					},
					"response": []
				}
			]
		},
		{
			"name": "defects",
			"item": [
				{
					"name": "authenticate",
					"event": [
						{
							"listen": "test",
							"script": {
								"exec": [
									"pm.environment.set(\"lwsso_cookie_key\", postman.getResponseCookie(\"LWSSO_COOKIE_KEY\").value)",
									"pm.environment.set(\"octane_user\", postman.getResponseCookie(\"OCTANE_USER\").value)",
									"//console.log (pm.environment.get(\"lwsso_cookie_key\"))",
									"//console.log (pm.environment.get(\"octane_user\"))",
									""
								],
								"type": "text/javascript"
							}
						}
					],
					"protocolProfileBehavior": {
						"disableUrlEncoding": false
					},
					"request": {
						"method": "POST",
						"header": [
							{
								"key": "Content-Type",
								"value": "application/json"
							}
						],
						"body": {
							"mode": "raw",
							"raw": "{\n    \"client_id\": \"{{client-id}}\",\n    \"client_secret\": \"{{client-secret}}\"\n}"
						},
						"url": {
							"raw": "http://{{baseUrl}}:{{port}}/authentication/sign_in",
							"protocol": "http",
							"host": [
								"{{baseUrl}}"
							],
							"port": "{{port}}",
							"path": [
								"authentication",
								"sign_in"
							]
						}
					},
					"response": []
				},
				{
					"name": "sap-soldto-party",
					"request": {
						"method": "POST",
						"header": [
							{
								"key": "Content-Type",
								"value": "application/json"
							},
							{
								"key": "LWSSO_COOKIE_KEY",
								"value": "{{lwsso_cookie_key}}"
							},
							{
								"key": "OCTANE_USER",
								"value": "{{octane_user}}"
							},
							{
								"key": "{{header-key}}",
								"value": "{{header-value}}"
							}
						],
						"body": {
							"mode": "raw",
							"raw": "{\n    \"data\": [\n        {\n            \"entity_type\": \"defect\",\n            \"label\": \"SAP Sold to Party\",\n            \"name\": \"sap_soldto_party_udf\",\n            \"subtype\": \"field_metadata_string\"\n        }\n    ]\n}"
						},
						"url": {
							"raw": "http://{{baseUrl}}:{{port}}/api/shared_spaces/{{ssid}}/workspaces/{{wsid}}/metadata_fields",
							"protocol": "http",
							"host": [
								"{{baseUrl}}"
							],
							"port": "{{port}}",
							"path": [
								"api",
								"shared_spaces",
								"{{ssid}}",
								"workspaces",
								"{{wsid}}",
								"metadata_fields"
							]
						}
					},
					"response": []
				},
				{
					"name": "sap-spnumber",
					"request": {
						"method": "POST",
						"header": [
							{
								"key": "Content-Type",
								"value": "application/json"
							},
							{
								"key": "LWSSO_COOKIE_KEY",
								"value": "{{lwsso_cookie_key}}"
							},
							{
								"key": "OCTANE_USER",
								"value": "{{octane_user}}"
							},
							{
								"key": "{{header-key}}",
								"value": "{{header-value}}"
							}
						],
						"body": {
							"mode": "raw",
							"raw": "{\n    \"data\": [\n        {\n            \"entity_type\": \"defect\",\n            \"label\": \"SAP SP Number\",\n            \"name\": \"sap_spnumber_udf\",\n            \"subtype\": \"field_metadata_string\"\n        }\n    ]\n}"
						},
						"url": {
							"raw": "http://{{baseUrl}}:8085/api/shared_spaces/{{ssid}}/workspaces/{{wsid}}/metadata_fields",
							"protocol": "http",
							"host": [
								"{{baseUrl}}"
							],
							"port": "8085",
							"path": [
								"api",
								"shared_spaces",
								"{{ssid}}",
								"workspaces",
								"{{wsid}}",
								"metadata_fields"
							]
						}
					},
					"response": []
				},
				{
					"name": "sap-status",
					"request": {
						"method": "POST",
						"header": [
							{
								"key": "Content-Type",
								"value": "application/json"
							},
							{
								"key": "LWSSO_COOKIE_KEY",
								"value": "{{lwsso_cookie_key}}"
							},
							{
								"key": "OCTANE_USER",
								"value": "{{octane_user}}"
							},
							{
								"key": "{{header-key}}",
								"value": "{{header-value}}"
							}
						],
						"body": {
							"mode": "raw",
							"raw": "{\n    \"data\": [\n        {\n            \"entity_type\": \"defect\",\n            \"label\": \"SAP Status\",\n            \"name\": \"sap_status_udf\",\n            \"subtype\": \"field_metadata_string\"\n        }\n    ]\n}"
						},
						"url": {
							"raw": "http://{{baseUrl}}:8085/api/shared_spaces/{{ssid}}/workspaces/{{wsid}}/metadata_fields",
							"protocol": "http",
							"host": [
								"{{baseUrl}}"
							],
							"port": "8085",
							"path": [
								"api",
								"shared_spaces",
								"{{ssid}}",
								"workspaces",
								"{{wsid}}",
								"metadata_fields"
							]
						}
					},
					"response": []
				},
				{
					"name": "sap-support-team",
					"request": {
						"method": "POST",
						"header": [
							{
								"key": "Content-Type",
								"value": "application/json"
							},
							{
								"key": "LWSSO_COOKIE_KEY",
								"value": "{{lwsso_cookie_key}}"
							},
							{
								"key": "OCTANE_USER",
								"value": "{{octane_user}}"
							},
							{
								"key": "{{header-key}}",
								"value": "{{header-value}}"
							}
						],
						"body": {
							"mode": "raw",
							"raw": "{\n    \"data\": [\n        {\n            \"entity_type\": \"defect\",\n            \"label\": \"SAP Support Team\",\n            \"name\": \"sap_support_team_udf\",\n            \"subtype\": \"field_metadata_string\"\n        }\n    ]\n}"
						},
						"url": {
							"raw": "http://{{baseUrl}}:8085/api/shared_spaces/{{ssid}}/workspaces/{{wsid}}/metadata_fields",
							"protocol": "http",
							"host": [
								"{{baseUrl}}"
							],
							"port": "8085",
							"path": [
								"api",
								"shared_spaces",
								"{{ssid}}",
								"workspaces",
								"{{wsid}}",
								"metadata_fields"
							]
						}
					},
					"response": []
				},
				{
					"name": "sap-system-client",
					"request": {
						"method": "POST",
						"header": [
							{
								"key": "Content-Type",
								"value": "application/json"
							},
							{
								"key": "LWSSO_COOKIE_KEY",
								"value": "{{lwsso_cookie_key}}"
							},
							{
								"key": "OCTANE_USER",
								"value": "{{octane_user}}"
							},
							{
								"key": "{{header-key}}",
								"value": "{{header-value}}"
							}
						],
						"body": {
							"mode": "raw",
							"raw": "{\n    \"data\": [\n        {\n            \"entity_type\": \"defect\",\n            \"label\": \"SAP System Client\",\n            \"name\": \"sap_system_client_udf\",\n            \"subtype\": \"field_metadata_string\"\n        }\n    ]\n}"
						},
						"url": {
							"raw": "http://{{baseUrl}}:8085/api/shared_spaces/{{ssid}}/workspaces/{{wsid}}/metadata_fields",
							"protocol": "http",
							"host": [
								"{{baseUrl}}"
							],
							"port": "8085",
							"path": [
								"api",
								"shared_spaces",
								"{{ssid}}",
								"workspaces",
								"{{wsid}}",
								"metadata_fields"
							]
						}
					},
					"response": []
				},
				{
					"name": "sap-system-component",
					"request": {
						"method": "POST",
						"header": [
							{
								"key": "Content-Type",
								"value": "application/json"
							},
							{
								"key": "LWSSO_COOKIE_KEY",
								"value": "{{lwsso_cookie_key}}"
							},
							{
								"key": "OCTANE_USER",
								"value": "{{octane_user}}"
							},
							{
								"key": "{{header-key}}",
								"value": "{{header-value}}"
							}
						],
						"body": {
							"mode": "raw",
							"raw": "{\n    \"data\": [\n        {\n            \"entity_type\": \"defect\",\n            \"label\": \"SAP System Component\",\n            \"name\": \"sap_system_component_udf\",\n            \"subtype\": \"field_metadata_string\"\n        }\n    ]\n}"
						},
						"url": {
							"raw": "http://{{baseUrl}}:8085/api/shared_spaces/{{ssid}}/workspaces/{{wsid}}/metadata_fields",
							"protocol": "http",
							"host": [
								"{{baseUrl}}"
							],
							"port": "8085",
							"path": [
								"api",
								"shared_spaces",
								"{{ssid}}",
								"workspaces",
								"{{wsid}}",
								"metadata_fields"
							]
						}
					},
					"response": []
				},
				{
					"name": "sap-system-id",
					"request": {
						"method": "POST",
						"header": [
							{
								"key": "Content-Type",
								"value": "application/json"
							},
							{
								"key": "LWSSO_COOKIE_KEY",
								"value": "{{lwsso_cookie_key}}"
							},
							{
								"key": "OCTANE_USER",
								"value": "{{octane_user}}"
							},
							{
								"key": "{{header-key}}",
								"value": "{{header-value}}"
							}
						],
						"body": {
							"mode": "raw",
							"raw": "{\n    \"data\": [\n        {\n            \"entity_type\": \"defect\",\n            \"label\": \"SAP System ID\",\n            \"name\": \"sap_system_id_udf\",\n            \"subtype\": \"field_metadata_string\"\n        }\n    ]\n}"
						},
						"url": {
							"raw": "http://{{baseUrl}}:8085/api/shared_spaces/{{ssid}}/workspaces/{{wsid}}/metadata_fields",
							"protocol": "http",
							"host": [
								"{{baseUrl}}"
							],
							"port": "8085",
							"path": [
								"api",
								"shared_spaces",
								"{{ssid}}",
								"workspaces",
								"{{wsid}}",
								"metadata_fields"
							]
						}
					},
					"response": []
				},
				{
					"name": "sap-system-inst-number",
					"request": {
						"method": "POST",
						"header": [
							{
								"key": "Content-Type",
								"value": "application/json"
							},
							{
								"key": "LWSSO_COOKIE_KEY",
								"value": "{{lwsso_cookie_key}}"
							},
							{
								"key": "OCTANE_USER",
								"value": "{{octane_user}}"
							},
							{
								"key": "{{header-key}}",
								"value": "{{header-value}}"
							}
						],
						"body": {
							"mode": "raw",
							"raw": "{\n    \"data\": [\n        {\n            \"entity_type\": \"defect\",\n            \"label\": \"SAP System Inst Number\",\n            \"name\": \"sap_system_inst_udf\",\n            \"subtype\": \"field_metadata_string\"\n        }\n    ]\n}"
						},
						"url": {
							"raw": "http://{{baseUrl}}:8085/api/shared_spaces/{{ssid}}/workspaces/{{wsid}}/metadata_fields",
							"protocol": "http",
							"host": [
								"{{baseUrl}}"
							],
							"port": "8085",
							"path": [
								"api",
								"shared_spaces",
								"{{ssid}}",
								"workspaces",
								"{{wsid}}",
								"metadata_fields"
							]
						}
					},
					"response": []
				},
				{
					"name": "sap-system-number",
					"request": {
						"method": "POST",
						"header": [
							{
								"key": "Content-Type",
								"value": "application/json"
							},
							{
								"key": "LWSSO_COOKIE_KEY",
								"value": "{{lwsso_cookie_key}}"
							},
							{
								"key": "OCTANE_USER",
								"value": "{{octane_user}}"
							},
							{
								"key": "{{header-key}}",
								"value": "{{header-value}}"
							}
						],
						"body": {
							"mode": "raw",
							"raw": "{\n    \"data\": [\n        {\n            \"entity_type\": \"defect\",\n            \"label\": \"SAP System Number\",\n            \"name\": \"sap_system_number_udf\",\n            \"subtype\": \"field_metadata_string\"\n        }\n    ]\n}"
						},
						"url": {
							"raw": "http://{{baseUrl}}:8085/api/shared_spaces/{{ssid}}/workspaces/{{wsid}}/metadata_fields",
							"protocol": "http",
							"host": [
								"{{baseUrl}}"
							],
							"port": "8085",
							"path": [
								"api",
								"shared_spaces",
								"{{ssid}}",
								"workspaces",
								"{{wsid}}",
								"metadata_fields"
							]
						}
					},
					"response": []
				},
				{
					"name": "sap-system-release",
					"request": {
						"method": "POST",
						"header": [
							{
								"key": "Content-Type",
								"value": "application/json"
							},
							{
								"key": "LWSSO_COOKIE_KEY",
								"value": "{{lwsso_cookie_key}}"
							},
							{
								"key": "OCTANE_USER",
								"value": "{{octane_user}}"
							},
							{
								"key": "{{header-key}}",
								"value": "{{header-value}}"
							}
						],
						"body": {
							"mode": "raw",
							"raw": "{\n    \"data\": [\n        {\n            \"entity_type\": \"defect\",\n            \"label\": \"SAP System Release\",\n            \"name\": \"sap_system_release_udf\",\n            \"subtype\": \"field_metadata_string\"\n        }\n    ]\n}"
						},
						"url": {
							"raw": "http://{{baseUrl}}:8085/api/shared_spaces/{{ssid}}/workspaces/{{wsid}}/metadata_fields",
							"protocol": "http",
							"host": [
								"{{baseUrl}}"
							],
							"port": "8085",
							"path": [
								"api",
								"shared_spaces",
								"{{ssid}}",
								"workspaces",
								"{{wsid}}",
								"metadata_fields"
							]
						}
					},
					"response": []
				},
				{
					"name": "sap-project-phase",
					"request": {
						"method": "POST",
						"header": [
							{
								"key": "Content-Type",
								"value": "application/json"
							},
							{
								"key": "LWSSO_COOKIE_KEY",
								"value": "{{lwsso_cookie_key}}"
							},
							{
								"key": "OCTANE_USER",
								"value": "{{octane_user}}"
							},
							{
								"key": "{{header-key}}",
								"value": "{{header-value}}"
							}
						],
						"body": {
							"mode": "raw",
							"raw": "{\n    \"data\": [\n        {\n            \"entity_type\": \"defect\",\n            \"label\": \"SAP Project Phase\",\n            \"name\": \"sap_project_phase_udf\",\n            \"subtype\": \"field_metadata_string\"\n        }\n    ]\n}"
						},
						"url": {
							"raw": "http://{{baseUrl}}:8085/api/shared_spaces/{{ssid}}/workspaces/{{wsid}}/metadata_fields",
							"protocol": "http",
							"host": [
								"{{baseUrl}}"
							],
							"port": "8085",
							"path": [
								"api",
								"shared_spaces",
								"{{ssid}}",
								"workspaces",
								"{{wsid}}",
								"metadata_fields"
							]
						}
					},
					"response": []
				},
				{
					"name": "sap-urgency",
					"request": {
						"method": "POST",
						"header": [
							{
								"key": "Content-Type",
								"value": "application/json"
							},
							{
								"key": "LWSSO_COOKIE_KEY",
								"value": "{{lwsso_cookie_key}}"
							},
							{
								"key": "OCTANE_USER",
								"value": "{{octane_user}}"
							},
							{
								"key": "{{header-key}}",
								"value": "{{header-value}}"
							}
						],
						"body": {
							"mode": "raw",
							"raw": "{\n    \"data\": [\n        {\n            \"entity_type\": \"defect\",\n            \"label\": \"SAP Urgency\",\n            \"name\": \"sap_urgency_udf\",\n            \"subtype\": \"field_metadata_string\"\n        }\n    ]\n}"
						},
						"url": {
							"raw": "http://{{baseUrl}}:8085/api/shared_spaces/{{ssid}}/workspaces/{{wsid}}/metadata_fields",
							"protocol": "http",
							"host": [
								"{{baseUrl}}"
							],
							"port": "8085",
							"path": [
								"api",
								"shared_spaces",
								"{{ssid}}",
								"workspaces",
								"{{wsid}}",
								"metadata_fields"
							]
						}
					},
					"response": []
				},
				{
					"name": "sap-category-id",
					"request": {
						"method": "POST",
						"header": [
							{
								"key": "Content-Type",
								"value": "application/json"
							},
							{
								"key": "LWSSO_COOKIE_KEY",
								"value": "{{lwsso_cookie_key}}"
							},
							{
								"key": "OCTANE_USER",
								"value": "{{octane_user}}"
							},
							{
								"key": "{{header-key}}",
								"value": "{{header-value}}"
							}
						],
						"body": {
							"mode": "raw",
							"raw": "{\n    \"data\": [\n        {\n            \"entity_type\": \"defect\",\n            \"label\": \"SAP Category ID\",\n            \"name\": \"sap_category_id_udf\",\n            \"subtype\": \"field_metadata_string\"\n        }\n    ]\n}"
						},
						"url": {
							"raw": "http://{{baseUrl}}:8085/api/shared_spaces/{{ssid}}/workspaces/{{wsid}}/metadata_fields",
							"protocol": "http",
							"host": [
								"{{baseUrl}}"
							],
							"port": "8085",
							"path": [
								"api",
								"shared_spaces",
								"{{ssid}}",
								"workspaces",
								"{{wsid}}",
								"metadata_fields"
							]
						}
					},
					"response": []
				},
				{
					"name": "sap-category-1",
					"request": {
						"method": "POST",
						"header": [
							{
								"key": "Content-Type",
								"value": "application/json"
							},
							{
								"key": "LWSSO_COOKIE_KEY",
								"value": "{{lwsso_cookie_key}}"
							},
							{
								"key": "OCTANE_USER",
								"value": "{{octane_user}}"
							},
							{
								"key": "{{header-key}}",
								"value": "{{header-value}}"
							}
						],
						"body": {
							"mode": "raw",
							"raw": "{\n    \"data\": [\n        {\n            \"entity_type\": \"defect\",\n            \"label\": \"SAP Category 1\",\n            \"name\": \"sap_category_1_udf\",\n            \"subtype\": \"field_metadata_string\"\n        }\n    ]\n}"
						},
						"url": {
							"raw": "http://{{baseUrl}}:8085/api/shared_spaces/{{ssid}}/workspaces/{{wsid}}/metadata_fields",
							"protocol": "http",
							"host": [
								"{{baseUrl}}"
							],
							"port": "8085",
							"path": [
								"api",
								"shared_spaces",
								"{{ssid}}",
								"workspaces",
								"{{wsid}}",
								"metadata_fields"
							]
						}
					},
					"response": []
				},
				{
					"name": "sap-category-2",
					"request": {
						"method": "POST",
						"header": [
							{
								"key": "Content-Type",
								"value": "application/json"
							},
							{
								"key": "LWSSO_COOKIE_KEY",
								"value": "{{lwsso_cookie_key}}"
							},
							{
								"key": "OCTANE_USER",
								"value": "{{octane_user}}"
							},
							{
								"key": "{{header-key}}",
								"value": "{{header-value}}"
							}
						],
						"body": {
							"mode": "raw",
							"raw": "{\n    \"data\": [\n        {\n            \"entity_type\": \"defect\",\n            \"label\": \"SAP Category 2\",\n            \"name\": \"sap_category_2_udf\",\n            \"subtype\": \"field_metadata_string\"\n        }\n    ]\n}"
						},
						"url": {
							"raw": "http://{{baseUrl}}:8085/api/shared_spaces/{{ssid}}/workspaces/{{wsid}}/metadata_fields",
							"protocol": "http",
							"host": [
								"{{baseUrl}}"
							],
							"port": "8085",
							"path": [
								"api",
								"shared_spaces",
								"{{ssid}}",
								"workspaces",
								"{{wsid}}",
								"metadata_fields"
							]
						}
					},
					"response": []
				},
				{
					"name": "sap-category-3",
					"request": {
						"method": "POST",
						"header": [
							{
								"key": "Content-Type",
								"value": "application/json"
							},
							{
								"key": "LWSSO_COOKIE_KEY",
								"value": "{{lwsso_cookie_key}}"
							},
							{
								"key": "OCTANE_USER",
								"value": "{{octane_user}}"
							},
							{
								"key": "{{header-key}}",
								"value": "{{header-value}}"
							}
						],
						"body": {
							"mode": "raw",
							"raw": "{\n    \"data\": [\n        {\n            \"entity_type\": \"defect\",\n            \"label\": \"SAP Category 3\",\n            \"name\": \"sap_category_3_udf\",\n            \"subtype\": \"field_metadata_string\"\n        }\n    ]\n}"
						},
						"url": {
							"raw": "http://{{baseUrl}}:8085/api/shared_spaces/{{ssid}}/workspaces/{{wsid}}/metadata_fields",
							"protocol": "http",
							"host": [
								"{{baseUrl}}"
							],
							"port": "8085",
							"path": [
								"api",
								"shared_spaces",
								"{{ssid}}",
								"workspaces",
								"{{wsid}}",
								"metadata_fields"
							]
						}
					},
					"response": []
				},
				{
					"name": "sap-category-4",
					"request": {
						"method": "POST",
						"header": [
							{
								"key": "Content-Type",
								"value": "application/json"
							},
							{
								"key": "LWSSO_COOKIE_KEY",
								"value": "{{lwsso_cookie_key}}"
							},
							{
								"key": "OCTANE_USER",
								"value": "{{octane_user}}"
							},
							{
								"key": "{{header-key}}",
								"value": "{{header-value}}"
							}
						],
						"body": {
							"mode": "raw",
							"raw": "{\n    \"data\": [\n        {\n            \"entity_type\": \"defect\",\n            \"label\": \"SAP Category 4\",\n            \"name\": \"sap_category_4_udf\",\n            \"subtype\": \"field_metadata_string\"\n        }\n    ]\n}"
						},
						"url": {
							"raw": "http://{{baseUrl}}:8085/api/shared_spaces/{{ssid}}/workspaces/{{wsid}}/metadata_fields",
							"protocol": "http",
							"host": [
								"{{baseUrl}}"
							],
							"port": "8085",
							"path": [
								"api",
								"shared_spaces",
								"{{ssid}}",
								"workspaces",
								"{{wsid}}",
								"metadata_fields"
							]
						}
					},
					"response": []
				},
				{
					"name": "sap-changed-at",
					"request": {
						"method": "POST",
						"header": [
							{
								"key": "Content-Type",
								"value": "application/json"
							},
							{
								"key": "LWSSO_COOKIE_KEY",
								"value": "{{lwsso_cookie_key}}"
							},
							{
								"key": "OCTANE_USER",
								"value": "{{octane_user}}"
							},
							{
								"key": "{{header-key}}",
								"value": "{{header-value}}"
							}
						],
						"body": {
							"mode": "raw",
							"raw": "{\n    \"data\": [\n        {\n            \"entity_type\": \"defect\",\n            \"label\": \"SAP Changed at\",\n            \"name\": \"sap_changed_at_udf\",\n            \"subtype\": \"field_metadata_date_time\"\n        }\n    ]\n}"
						},
						"url": {
							"raw": "http://{{baseUrl}}:8085/api/shared_spaces/{{ssid}}/workspaces/{{wsid}}/metadata_fields",
							"protocol": "http",
							"host": [
								"{{baseUrl}}"
							],
							"port": "8085",
							"path": [
								"api",
								"shared_spaces",
								"{{ssid}}",
								"workspaces",
								"{{wsid}}",
								"metadata_fields"
							]
						}
					},
					"response": []
				},
				{
					"name": "sap-config-item",
					"request": {
						"method": "POST",
						"header": [
							{
								"key": "Content-Type",
								"value": "application/json"
							},
							{
								"key": "LWSSO_COOKIE_KEY",
								"value": "{{lwsso_cookie_key}}"
							},
							{
								"key": "OCTANE_USER",
								"value": "{{octane_user}}"
							},
							{
								"key": "{{header-key}}",
								"value": "{{header-value}}"
							}
						],
						"body": {
							"mode": "raw",
							"raw": "{\n    \"data\": [\n        {\n            \"entity_type\": \"defect\",\n            \"label\": \"SAP Config Item\",\n            \"name\": \"sap_config_item_udf\",\n            \"subtype\": \"field_metadata_string\"\n        }\n    ]\n}"
						},
						"url": {
							"raw": "http://{{baseUrl}}:8085/api/shared_spaces/{{ssid}}/workspaces/{{wsid}}/metadata_fields",
							"protocol": "http",
							"host": [
								"{{baseUrl}}"
							],
							"port": "8085",
							"path": [
								"api",
								"shared_spaces",
								"{{ssid}}",
								"workspaces",
								"{{wsid}}",
								"metadata_fields"
							]
						}
					},
					"response": []
				},
				{
					"name": "sap-created-at",
					"request": {
						"method": "POST",
						"header": [
							{
								"key": "Content-Type",
								"value": "application/json"
							},
							{
								"key": "LWSSO_COOKIE_KEY",
								"value": "{{lwsso_cookie_key}}"
							},
							{
								"key": "OCTANE_USER",
								"value": "{{octane_user}}"
							},
							{
								"key": "{{header-key}}",
								"value": "{{header-value}}"
							}
						],
						"body": {
							"mode": "raw",
							"raw": "{\n    \"data\": [\n        {\n            \"entity_type\": \"defect\",\n            \"label\": \"SAP Created at\",\n            \"name\": \"sap_created_at_udf\",\n            \"subtype\": \"field_metadata_date_time\"\n        }\n    ]\n}"
						},
						"url": {
							"raw": "http://{{baseUrl}}:8085/api/shared_spaces/{{ssid}}/workspaces/{{wsid}}/metadata_fields",
							"protocol": "http",
							"host": [
								"{{baseUrl}}"
							],
							"port": "8085",
							"path": [
								"api",
								"shared_spaces",
								"{{ssid}}",
								"workspaces",
								"{{wsid}}",
								"metadata_fields"
							]
						}
					},
					"response": []
				},
				{
					"name": "sap-due-by",
					"request": {
						"method": "POST",
						"header": [
							{
								"key": "Content-Type",
								"value": "application/json"
							},
							{
								"key": "LWSSO_COOKIE_KEY",
								"value": "{{lwsso_cookie_key}}"
							},
							{
								"key": "OCTANE_USER",
								"value": "{{octane_user}}"
							},
							{
								"key": "{{header-key}}",
								"value": "{{header-value}}"
							}
						],
						"body": {
							"mode": "raw",
							"raw": "{\n    \"data\": [\n        {\n            \"entity_type\": \"defect\",\n            \"label\": \"SAP Due by\",\n            \"name\": \"sap_due_by_udf\",\n            \"subtype\": \"field_metadata_date_time\"\n        }\n    ]\n}"
						},
						"url": {
							"raw": "http://{{baseUrl}}:8085/api/shared_spaces/{{ssid}}/workspaces/{{wsid}}/metadata_fields",
							"protocol": "http",
							"host": [
								"{{baseUrl}}"
							],
							"port": "8085",
							"path": [
								"api",
								"shared_spaces",
								"{{ssid}}",
								"workspaces",
								"{{wsid}}",
								"metadata_fields"
							]
						}
					},
					"response": []
				},
				{
					"name": "sap-first-respby",
					"request": {
						"method": "POST",
						"header": [
							{
								"key": "Content-Type",
								"value": "application/json"
							},
							{
								"key": "LWSSO_COOKIE_KEY",
								"value": "{{lwsso_cookie_key}}"
							},
							{
								"key": "OCTANE_USER",
								"value": "{{octane_user}}"
							},
							{
								"key": "{{header-key}}",
								"value": "{{header-value}}"
							}
						],
						"body": {
							"mode": "raw",
							"raw": "{\n    \"data\": [\n        {\n            \"entity_type\": \"defect\",\n            \"label\": \"SAP First Resp by\",\n            \"name\": \"sap_first_respby_udf\",\n            \"subtype\": \"field_metadata_date_time\"\n        }\n    ]\n}"
						},
						"url": {
							"raw": "http://{{baseUrl}}:8085/api/shared_spaces/{{ssid}}/workspaces/{{wsid}}/metadata_fields",
							"protocol": "http",
							"host": [
								"{{baseUrl}}"
							],
							"port": "8085",
							"path": [
								"api",
								"shared_spaces",
								"{{ssid}}",
								"workspaces",
								"{{wsid}}",
								"metadata_fields"
							]
						}
					},
					"response": []
				},
				{
					"name": "sap-impact",
					"request": {
						"method": "POST",
						"header": [
							{
								"key": "Content-Type",
								"value": "application/json"
							},
							{
								"key": "LWSSO_COOKIE_KEY",
								"value": "{{lwsso_cookie_key}}"
							},
							{
								"key": "OCTANE_USER",
								"value": "{{octane_user}}"
							},
							{
								"key": "{{header-key}}",
								"value": "{{header-value}}"
							}
						],
						"body": {
							"mode": "raw",
							"raw": "{\n    \"data\": [\n        {\n            \"entity_type\": \"defect\",\n            \"label\": \"SAP Impact\",\n            \"name\": \"sap_impact_udf\",\n            \"subtype\": \"field_metadata_string\"\n        }\n    ]\n}"
						},
						"url": {
							"raw": "http://{{baseUrl}}:8085/api/shared_spaces/{{ssid}}/workspaces/{{wsid}}/metadata_fields",
							"protocol": "http",
							"host": [
								"{{baseUrl}}"
							],
							"port": "8085",
							"path": [
								"api",
								"shared_spaces",
								"{{ssid}}",
								"workspaces",
								"{{wsid}}",
								"metadata_fields"
							]
						}
					},
					"response": []
				},
				{
					"name": "sap-incident-id",
					"request": {
						"method": "POST",
						"header": [
							{
								"key": "Content-Type",
								"value": "application/json"
							},
							{
								"key": "LWSSO_COOKIE_KEY",
								"value": "{{lwsso_cookie_key}}"
							},
							{
								"key": "OCTANE_USER",
								"value": "{{octane_user}}"
							},
							{
								"key": "{{header-key}}",
								"value": "{{header-value}}"
							}
						],
						"body": {
							"mode": "raw",
							"raw": "{\n    \"data\": [\n        {\n            \"entity_type\": \"defect\",\n            \"label\": \"SAP Incident ID\",\n            \"name\": \"sap_incident_id_udf\",\n            \"subtype\": \"field_metadata_string\"\n        }\n    ]\n}"
						},
						"url": {
							"raw": "http://{{baseUrl}}:8085/api/shared_spaces/{{ssid}}/workspaces/{{wsid}}/metadata_fields",
							"protocol": "http",
							"host": [
								"{{baseUrl}}"
							],
							"port": "8085",
							"path": [
								"api",
								"shared_spaces",
								"{{ssid}}",
								"workspaces",
								"{{wsid}}",
								"metadata_fields"
							]
						}
					},
					"response": []
				},
				{
					"name": "sap-project",
					"request": {
						"method": "POST",
						"header": [
							{
								"key": "Content-Type",
								"value": "application/json"
							},
							{
								"key": "LWSSO_COOKIE_KEY",
								"value": "{{lwsso_cookie_key}}"
							},
							{
								"key": "OCTANE_USER",
								"value": "{{octane_user}}"
							},
							{
								"key": "{{header-key}}",
								"value": "{{header-value}}"
							}
						],
						"body": {
							"mode": "raw",
							"raw": "{\n    \"data\": [\n        {\n            \"entity_type\": \"defect\",\n            \"label\": \"SAP Project\",\n            \"name\": \"sap_project_udf\",\n            \"subtype\": \"field_metadata_string\"\n        }\n    ]\n}"
						},
						"url": {
							"raw": "http://{{baseUrl}}:8085/api/shared_spaces/{{ssid}}/workspaces/{{wsid}}/metadata_fields",
							"protocol": "http",
							"host": [
								"{{baseUrl}}"
							],
							"port": "8085",
							"path": [
								"api",
								"shared_spaces",
								"{{ssid}}",
								"workspaces",
								"{{wsid}}",
								"metadata_fields"
							]
						}
					},
					"response": []
				},
				{
					"name": "sap-url",
					"request": {
						"method": "POST",
						"header": [
							{
								"key": "Content-Type",
								"value": "application/json"
							},
							{
								"key": "LWSSO_COOKIE_KEY",
								"value": "{{lwsso_cookie_key}}"
							},
							{
								"key": "OCTANE_USER",
								"value": "{{octane_user}}"
							},
							{
								"key": "{{header-key}}",
								"value": "{{header-value}}"
							}
						],
						"body": {
							"mode": "raw",
							"raw": "{\n    \"data\": [\n        {\n            \"entity_type\": \"defect\",\n            \"label\": \"SAP URL\",\n            \"name\": \"sap_url_udf\",\n            \"subtype\": \"field_metadata_string\"\n        }\n    ]\n}"
						},
						"url": {
							"raw": "http://{{baseUrl}}:8085/api/shared_spaces/{{ssid}}/workspaces/{{wsid}}/metadata_fields",
							"protocol": "http",
							"host": [
								"{{baseUrl}}"
							],
							"port": "8085",
							"path": [
								"api",
								"shared_spaces",
								"{{ssid}}",
								"workspaces",
								"{{wsid}}",
								"metadata_fields"
							]
						}
					},
					"response": []
				},
				{
					"name": "sap-priority",
					"request": {
						"method": "POST",
						"header": [
							{
								"key": "Content-Type",
								"value": "application/json"
							},
							{
								"key": "LWSSO_COOKIE_KEY",
								"value": "{{lwsso_cookie_key}}"
							},
							{
								"key": "OCTANE_USER",
								"value": "{{octane_user}}"
							},
							{
								"key": "{{header-key}}",
								"value": "{{header-value}}"
							}
						],
						"body": {
							"mode": "raw",
							"raw": "{\n    \"data\": [\n        {\n            \"entity_type\": \"defect\",\n            \"label\": \"SAP Priority\",\n            \"name\": \"sap_priority_udf\",\n            \"subtype\": \"field_metadata_string\"\n        }\n    ]\n}"
						},
						"url": {
							"raw": "http://{{baseUrl}}:8085/api/shared_spaces/{{ssid}}/workspaces/{{wsid}}/metadata_fields",
							"protocol": "http",
							"host": [
								"{{baseUrl}}"
							],
							"port": "8085",
							"path": [
								"api",
								"shared_spaces",
								"{{ssid}}",
								"workspaces",
								"{{wsid}}",
								"metadata_fields"
							]
						}
					},
					"response": []
				},
				{
					"name": "sap-attach-count",
					"request": {
						"method": "POST",
						"header": [
							{
								"key": "Content-Type",
								"value": "application/json"
							},
							{
								"key": "LWSSO_COOKIE_KEY",
								"value": "{{lwsso_cookie_key}}"
							},
							{
								"key": "OCTANE_USER",
								"value": "{{octane_user}}"
							},
							{
								"key": "{{header-key}}",
								"value": "{{header-value}}"
							}
						],
						"body": {
							"mode": "raw",
							"raw": "{\n    \"data\": [\n        {\n            \"entity_type\": \"defect\",\n            \"label\": \"SAP Attachment Count\",\n            \"name\": \"sap_attachnr_udf\",\n            \"subtype\": \"field_metadata_string\"\n        }\n    ]\n}"
						},
						"url": {
							"raw": "http://{{baseUrl}}:8085/api/shared_spaces/{{ssid}}/workspaces/{{wsid}}/metadata_fields",
							"protocol": "http",
							"host": [
								"{{baseUrl}}"
							],
							"port": "8085",
							"path": [
								"api",
								"shared_spaces",
								"{{ssid}}",
								"workspaces",
								"{{wsid}}",
								"metadata_fields"
							]
						}
					},
					"response": []
				},
				{
					"name": "sap-message-processor",
					"request": {
						"method": "POST",
						"header": [
							{
								"key": "Content-Type",
								"value": "application/json"
							},
							{
								"key": "LWSSO_COOKIE_KEY",
								"value": "{{lwsso_cookie_key}}"
							},
							{
								"key": "OCTANE_USER",
								"value": "{{octane_user}}"
							},
							{
								"key": "{{header-key}}",
								"value": "{{header-value}}"
							}
						],
						"body": {
							"mode": "raw",
							"raw": "{\n    \"data\": [\n        {\n            \"entity_type\": \"defect\",\n            \"label\": \"SAP Message Processor\",\n            \"name\": \"sap_message_proc_udf\",\n            \"subtype\": \"field_metadata_string\"\n        }\n    ]\n}"
						},
						"url": {
							"raw": "http://{{baseUrl}}:8085/api/shared_spaces/{{ssid}}/workspaces/{{wsid}}/metadata_fields",
							"protocol": "http",
							"host": [
								"{{baseUrl}}"
							],
							"port": "8085",
							"path": [
								"api",
								"shared_spaces",
								"{{ssid}}",
								"workspaces",
								"{{wsid}}",
								"metadata_fields"
							]
						}
					},
					"response": []
				},
				{
					"name": "sap-incident-type-id",
					"request": {
						"method": "POST",
						"header": [
							{
								"key": "Content-Type",
								"value": "application/json"
							},
							{
								"key": "LWSSO_COOKIE_KEY",
								"value": "{{lwsso_cookie_key}}"
							},
							{
								"key": "OCTANE_USER",
								"value": "{{octane_user}}"
							},
							{
								"key": "{{header-key}}",
								"value": "{{header-value}}"
							}
						],
						"body": {
							"mode": "raw",
							"raw": "{\n    \"data\": [\n        {\n            \"entity_type\": \"defect\",\n            \"label\": \"SAP Incident Type ID\",\n            \"name\": \"sap_incident_type_udf\",\n            \"subtype\": \"field_metadata_string\"\n        }\n    ]\n}"
						},
						"url": {
							"raw": "http://{{baseUrl}}:8085/api/shared_spaces/{{ssid}}/workspaces/{{wsid}}/metadata_fields",
							"protocol": "http",
							"host": [
								"{{baseUrl}}"
							],
							"port": "8085",
							"path": [
								"api",
								"shared_spaces",
								"{{ssid}}",
								"workspaces",
								"{{wsid}}",
								"metadata_fields"
							]
						}
					},
					"response": []
				},
				{
					"name": "sap-def-form",
					"event": [
						{
							"listen": "test",
							"script": {
								"exec": [
									"var jsData = JSON.parse(responseBody);\r",
									"\r",
									"var id = jsData.data[0].id;\r",
									"pm.environment.set(\"def-form-id\", id);"
								],
								"type": "text/javascript"
							}
						}
					],
					"request": {
						"method": "POST",
						"header": [
							{
								"key": "Content-Type",
								"value": "application/json"
							},
							{
								"key": "LWSSO_COOKIE_KEY",
								"value": "{{lwsso_cookie_key}}"
							},
							{
								"key": "OCTANE_USER",
								"value": "{{octane_user}}"
							},
							{
								"key": "{{header-key}}",
								"value": "{{header-value}}"
							}
						],
						"body": {
							"mode": "raw",
							"raw": "{\n    \"data\": [\n        {\n            \"name\": \"sap-connector-def-form\",\n            \"body\": {\n                \"layout\": {\n                    \"sections\": [\n                        {\n                            \"title\": \"SAP Connector\",\n                            \"fields\": [\n                                {\n                                    \"name\": \"sap_attachnr_udf\",\n                                    \"size\": \"medium\"\n                                },\n                                {\n                                    \"name\": \"sap_category_1_udf\",\n                                    \"size\": \"large\"\n                                },\n                                {\n                                    \"name\": \"sap_category_2_udf\",\n                                    \"size\": \"large\"\n                                },\n                                {\n                                    \"name\": \"sap_category_3_udf\",\n                                    \"size\": \"large\"\n                                },\n                                {\n                                    \"name\": \"sap_category_4_udf\",\n                                    \"size\": \"large\"\n                                },\n                                {\n                                    \"name\": \"sap_category_id_udf\",\n                                    \"size\": \"medium\"\n                                },\n                                {\n                                    \"name\": \"sap_changed_at_udf\",\n                                    \"size\": \"medium\"\n                                },\n                                {\n                                    \"name\": \"sap_config_item_udf\",\n                                    \"size\": \"medium\"\n                                },\n                                {\n                                    \"name\": \"sap_created_at_udf\",\n                                    \"size\": \"medium\"\n                                },\n                                {\n                                    \"name\": \"sap_due_by_udf\",\n                                    \"size\": \"medium\"\n                                },\n                                {\n                                    \"name\": \"sap_first_respby_udf\",\n                                    \"size\": \"medium\"\n                                },\n                                {\n                                    \"name\": \"sap_impact_udf\",\n                                    \"size\": \"medium\"\n                                },\n                                {\n                                    \"name\": \"sap_incident_id_udf\",\n                                    \"size\": \"medium\"\n                                },\n                                {\n                                    \"name\": \"sap_incident_type_udf\",\n                                    \"size\": \"medium\"\n                                },\n                                {\n                                    \"name\": \"sap_message_proc_udf\",\n                                    \"size\": \"medium\"\n                                },\n                                {\n                                    \"name\": \"sap_priority_udf\",\n                                    \"size\": \"medium\"\n                                },\n                                {\n                                    \"name\": \"sap_project_udf\",\n                                    \"size\": \"medium\"\n                                },\n                                {\n                                    \"name\": \"sap_project_phase_udf\",\n                                    \"size\": \"medium\"\n                                },\n                                {\n                                    \"name\": \"sap_soldto_party_udf\",\n                                    \"size\": \"medium\"\n                                },\n                                {\n                                    \"name\": \"sap_spnumber_udf\",\n                                    \"size\": \"medium\"\n                                },\n                                {\n                                    \"name\": \"sap_status_udf\",\n                                    \"size\": \"medium\"\n                                },\n                                {\n                                    \"name\": \"sap_support_team_udf\",\n                                    \"size\": \"medium\"\n                                },\n                                {\n                                    \"name\": \"sap_system_client_udf\",\n                                    \"size\": \"medium\"\n                                },\n                                {\n                                    \"name\": \"sap_system_component_udf\",\n                                    \"size\": \"medium\"\n                                },\n                                {\n                                    \"name\": \"sap_system_id_udf\",\n                                    \"size\": \"medium\"\n                                },\n                                {\n                                    \"name\": \"sap_system_inst_udf\",\n                                    \"size\": \"medium\"\n                                },\n                                {\n                                    \"name\": \"sap_system_number_udf\",\n                                    \"size\": \"medium\"\n                                },\n                                {\n                                    \"name\": \"sap_system_release_udf\",\n                                    \"size\": \"medium\"\n                                },\n                                {\n                                    \"name\": \"sap_urgency_udf\",\n                                    \"size\": \"medium\"\n                                },\n                                {\n                                    \"name\": \"sap_url_udf\",\n                                    \"size\": \"medium\"\n                                }\n                            ]\n                        },\n                        {\n                            \"title\": \"General\",\n                            \"fields\": [\n                                {\n                                    \"name\": \"description\",\n                                    \"size\": \"large\"\n                                }\n                            ]\n                        }\n                    ]\n                }\n            },\n            \"is_default\": 0,\n            \"entity_type\": \"work_item\",\n            \"entity_subtype\": \"defect\"\n        }\n    ]\n}"
						},
						"url": {
							"raw": "http://{{baseUrl}}:8085/api/shared_spaces/{{ssid}}/workspaces/{{wsid}}/form_layouts",
							"protocol": "http",
							"host": [
								"{{baseUrl}}"
							],
							"port": "8085",
							"path": [
								"api",
								"shared_spaces",
								"{{ssid}}",
								"workspaces",
								"{{wsid}}",
								"form_layouts"
							]
						}
					},
					"response": []
				},
				{
					"name": "sap-def-form-make-default",
					"event": [
						{
							"listen": "test",
							"script": {
								"exec": [
									""
								],
								"type": "text/javascript"
							}
						}
					],
					"request": {
						"method": "PUT",
						"header": [
							{
								"key": "Content-Type",
								"value": "application/json"
							},
							{
								"key": "LWSSO_COOKIE_KEY",
								"value": "{{lwsso_cookie_key}}"
							},
							{
								"key": "OCTANE_USER",
								"value": "{{octane_user}}"
							},
							{
								"key": "{{header-key}}",
								"value": "{{header-value}}"
							}
						],
						"body": {
							"mode": "raw",
							"raw": "{\n    \"data\": [\n        {\n            \"is_default\": 1,\n            \"id\": \"{{def-form-id}}\"\n        },\n        {\n            \"is_default\": 3,\n            \"id\": \"{{def-form-id}}\"\n        }\n    ]\n}"
						},
						"url": {
							"raw": "http://{{baseUrl}}:8085/api/shared_spaces/{{ssid}}/workspaces/{{wsid}}/form_layouts/",
							"protocol": "http",
							"host": [
								"{{baseUrl}}"
							],
							"port": "8085",
							"path": [
								"api",
								"shared_spaces",
								"{{ssid}}",
								"workspaces",
								"{{wsid}}",
								"form_layouts",
								""
							]
						}
					},
					"response": []
				}
			]
		}
	],
	"event": [
		{
			"listen": "prerequest",
			"script": {
				"type": "text/javascript",
				"exec": [
					""
				]
			}
		},
		{
			"listen": "test",
			"script": {
				"type": "text/javascript",
				"exec": [
					""
				]
			}
		}
	]
}